splinator/__init__.py
splinator/_version.py
splinator/estimators.py
splinator/metrics.py
splinator/monotonic_spline.py
splinator-0.3.0.dist-info/METADATA
splinator-0.3.0.dist-info/WHEEL
splinator-0.3.0.dist-info/licenses/LICENSE
splinator-0.3.0.dist-info/RECORD
