Metadata-Version: 2.4
Name: splinator
Version: 0.3.0
Summary: Python library for fitting linear-spline based logistic regression for calibration.
Author-email: Jiarui Xu <jiarui.xu@affirm.com>
License: BSD-3-Clause
License-File: LICENSE
Keywords: calibration,logistic,regression,spline
Classifier: License :: OSI Approved :: BSD License
Classifier: Operating System :: OS Independent
Classifier: Programming Language :: Python :: 3
Classifier: Programming Language :: Python :: 3.9
Classifier: Programming Language :: Python :: 3.10
Classifier: Programming Language :: Python :: 3.11
Classifier: Programming Language :: Python :: 3.12
Requires-Python: >=3.9
Requires-Dist: numpy>=1.19.0
Requires-Dist: pandas>=1.3.0
Requires-Dist: scikit-learn>=1.0.0
Requires-Dist: scipy>=1.6.0
Provides-Extra: dev
Requires-Dist: jupyter>=1.0.0; extra == 'dev'
Requires-Dist: matplotlib>=3.5.3; extra == 'dev'
Requires-Dist: mypy>=0.971; extra == 'dev'
Requires-Dist: pytest>=7.1.2; extra == 'dev'
